hi.py
helloai/__init__.py
helloai/__main__.py
helloai/builtins.py
helloai/runner.py
helloai/version.py
helloai/core/__init__.py
helloai/core/api.py
helloai/core/camera.py
helloai/core/colors.py
helloai/core/config.py
helloai/core/core.py
helloai/core/display.py
helloai/core/helper.py
helloai/core/image.py
helloai/core/lineplot_wnd.py
helloai/core/movie.py
helloai/core/mytimer.py
helloai/core/singlestore.py
helloai/core/sketch.py
helloai/core/table_wnd.py
helloai/core/trackbarwin.py
helloai/core/vector.py
helloai/core/video.py
helloai/core/video_reader.py
helloai/core/video_writer.py
helloai/core/virtualcamera.py
helloai/core/window.py
helloai/ext/__init__.py
helloai/ext/aruco/__init__.py
helloai/ext/aruco/aruco.py
helloai/ext/aruco/aruco_test.py
helloai/ext/classifier/__init__.py
helloai/ext/classifier/classifier.py
helloai/ext/face_detector/__init__.py
helloai/ext/face_detector/face_detector.bak.py
helloai/ext/face_detector/face_detector.py
helloai/ext/hands_detector/__init__.py
helloai/ext/hands_detector/hands_detector.bak.py
helloai/ext/hands_detector/hands_detector.py
helloai/ext/ocr/__init__.py
helloai/ext/ocr/ocr.py
helloai/ext/pose_detector/__init__.py
helloai/ext/pose_detector/pose_detector.py
helloai/ext/regressor/__init__.py
helloai/ext/regressor/regressor.py
helloai/ext/tmimage/__init__.py
helloai/ext/tmimage/tm_imageproject.py
helloai/ext/tts/__init__.py
helloai/ext/tts/tts.py
helloai/utils/PID.py
helloai/utils/__init__.py
helloai/utils/csv_reader.py
helloai/utils/csv_writer.py
helloai/utils/cvzone.py
helloai/utils/fetcher.py
helloai/utils/rand.py
helloai/utils/thread_controler.py
helloai/utils/time.py
helloai/utils/utils.py
helloai/utils/voc.py
helloai-3.8.dist-info/licenses/LICENSE
helloai-3.8.dist-info/METADATA
helloai-3.8.dist-info/WHEEL
helloai-3.8.dist-info/entry_points.txt
helloai-3.8.dist-info/top_level.txt
helloai-3.8.dist-info/RECORD
